min_max_heap/__init__.py
min_max_heap/min_max_heap.py
min_max_heap/utils.py
min_max_heap-1.0.1.dist-info/LICENSE
min_max_heap-1.0.1.dist-info/METADATA
min_max_heap-1.0.1.dist-info/WHEEL
min_max_heap-1.0.1.dist-info/top_level.txt
min_max_heap-1.0.1.dist-info/RECORD
