Metadata-Version: 2.1
Name: min-max-heap
Version: 1.0.1
Summary: A implementation of MinMaxHeap with Python language.
Home-page: https://github.com/hfi/min-max-heap
Author: Yuan Yang
Author-email: i@yangyuan.me
License: The MIT License (MIT)
Platform: Any
Classifier: Programming Language :: Python
Classifier: Programming Language :: Python :: 3
Classifier: Programming Language :: Python :: 3.6
Classifier: Programming Language :: Python :: 3.7
Classifier: Programming Language :: Python :: 3.8
Classifier: Programming Language :: Python :: 3.9
Classifier: Programming Language :: Python :: 3.10
License-File: LICENSE
